rfb_driver_bases/__init__.py
rfb_driver_bases/__version__.py
rfb_driver_bases/drv_base_pwr.py
rfb_driver_bases/drv_base_status.py
rfb_driver_bases-0.0.1.dist-info/LICENSE.txt
rfb_driver_bases-0.0.1.dist-info/METADATA
rfb_driver_bases-0.0.1.dist-info/WHEEL
rfb_driver_bases-0.0.1.dist-info/top_level.txt
rfb_driver_bases-0.0.1.dist-info/RECORD
