Metadata-Version: 2.1
Name: rfb_driver_bases
Version: 0.0.1
Summary: A simple drvier used as base for the other drivers
Author-email: Raldea <r.aldea.csic+pypi@gmail.com>, Marius Crisan <mariuscrsn+pypi@gmail.com>, Pablo Pastor <pastorpflores+pypi@gmail.com>, Javier Sanz <javiersanzmoline@gmail.com>, Luis Roche <luis.roche@hotmail.com>
Maintainer-email: Raldea <r.aldea.csic+pypi@gmail.com>
License: GNU GENERAL PUBLIC LICENSE
Project-URL: Homepage, https://github.com/GIDEF-RFB/Battery-Cycler-Drivers
Project-URL: Bug Reports, https://github.com/GIDEF-RFB/Battery-Cycler-Drivers/issues
Project-URL: Bug Tracker, https://github.com/GIDEF-RFB/Battery-Cycler-Drivers/issues
Project-URL: Source, https://github.com/GIDEF-RFB/Battery-Cycler-Drivers/code/drv_base/src/rfb_driver_bases
Project-URL: Funding, https://donate.pypi.org
Keywords: Embedded Systems,driver,base,OOP
Classifier: Development Status :: 3 - Alpha
Classifier: Topic :: Software Development :: Embedded Systems
Classifier: Topic :: Database :: Front-Ends
Classifier: Topic :: Software Development :: Libraries :: Python Modules
Classifier: Operating System :: OS Independent
Classifier: License :: OSI Approved :: GNU Affero General Public License v3
Classifier: Programming Language :: Python :: 3
Classifier: Programming Language :: Python :: 3.7
Classifier: Programming Language :: Python :: 3.8
Classifier: Programming Language :: Python :: 3.9
Classifier: Programming Language :: Python :: 3.10
Classifier: Programming Language :: Python :: 3.11
Classifier: Programming Language :: Python :: 3 :: Only
Classifier: Programming Language :: SQL
Requires-Python: >=3.7
License-File: LICENSE.txt
Requires-Dist: rfb-logger-tool >=0.0.1
